simcats_datasets/__init__.py
simcats_datasets/generation/__init__.py
simcats_datasets/generation/_create_dataset.py
simcats_datasets/generation/_create_simulated_dataset.py
simcats_datasets/loading/__init__.py
simcats_datasets/loading/_load_dataset.py
simcats_datasets/loading/load_ground_truth.py
simcats_datasets/loading/pytorch.py
simcats_datasets/support_functions/__init__.py
simcats_datasets/support_functions/_json_encoders.py
simcats_datasets/support_functions/clip_line_to_rectangle.py
simcats_datasets/support_functions/convert_lines.py
simcats_datasets/support_functions/data_preprocessing.py
simcats_datasets/support_functions/get_lead_transition_labels.py
simcats_datasets/support_functions/pytorch_format_output.py
simcats_datasets-2.5.0.dist-info/LICENSE
simcats_datasets-2.5.0.dist-info/METADATA
simcats_datasets-2.5.0.dist-info/WHEEL
simcats_datasets-2.5.0.dist-info/top_level.txt
simcats_datasets-2.5.0.dist-info/RECORD
