Metadata-Version: 2.1
Name: simcats-datasets
Version: 2.5.0
Summary: SimCATS-Datasets is a Python package that simplifies the creation and loading of SimCATS datasets. 
Author-email: Fabian Hader <f.hader@fz-juelich.de>, Fabian Fuchs <f.fuchs@fz-juelich.de>, Karin Havemann <k.havemann@fz-juelich.de>, Sarah Fleitmann <s.fleitmann@fz-juelich.de>, Jan Vogelbruch <j.vogelbruch@fz-juelich.de>
License: GNU GENERAL PUBLIC LICENSE
Project-URL: homepage, https://github.com/f-hader/SimCATS-Datasets
Project-URL: documentation, https://simcats-datasets.readthedocs.io
Project-URL: source, https://github.com/f-hader/SimCATS-Datasets
Project-URL: tracker, https://github.com/f-hader/SimCATS-Datasets/issues
Classifier: License :: OSI Approved :: GNU General Public License v3 or later (GPLv3+)
Classifier: Development Status :: 5 - Production/Stable
Classifier: Intended Audience :: Science/Research
Classifier: Programming Language :: Python
Classifier: Programming Language :: Python :: 3
Classifier: Programming Language :: Python :: 3.7
Classifier: Programming Language :: Python :: 3.8
Classifier: Programming Language :: Python :: 3.9
Classifier: Programming Language :: Python :: 3.10
Classifier: Programming Language :: Python :: 3.11
Classifier: Topic :: Scientific/Engineering
Classifier: Typing :: Typed
Requires-Python: >=3.7
License-File: LICENSE
Requires-Dist: bezier
Requires-Dist: bm3d
Requires-Dist: h5py
Requires-Dist: hdf5storage
Requires-Dist: numpy
Requires-Dist: opencv-python
Requires-Dist: pandas
Requires-Dist: parallelbar
Requires-Dist: parse
Requires-Dist: scikit-image
Requires-Dist: simcats >=1.2.0
Requires-Dist: torch
Requires-Dist: tqdm
Requires-Dist: xarray
